hgdemandimport/__init__.py
hgdemandimport/demandimportpy3.py
hgdemandimport/tracing.py
hgext/__init__.py
hgext/absorb.py
hgext/acl.py
hgext/amend.py
hgext/automv.py
hgext/beautifygraph.py
hgext/blackbox.py
hgext/bookflow.py
hgext/bugzilla.py
hgext/censor.py
hgext/children.py
hgext/churn.py
hgext/clonebundles.py
hgext/closehead.py
hgext/commitextras.py
hgext/eol.py
hgext/extdiff.py
hgext/factotum.py
hgext/fastexport.py
hgext/fetch.py
hgext/fix.py
hgext/githelp.py
hgext/gpg.py
hgext/graphlog.py
hgext/hgk.py
hgext/histedit.py
hgext/journal.py
hgext/keyword.py
hgext/logtoprocess.py
hgext/mq.py
hgext/notify.py
hgext/pager.py
hgext/patchbomb.py
hgext/phabricator.py
hgext/purge.py
hgext/rebase.py
hgext/record.py
hgext/releasenotes.py
hgext/relink.py
hgext/remotenames.py
hgext/schemes.py
hgext/share.py
hgext/show.py
hgext/sparse.py
hgext/split.py
hgext/strip.py
hgext/transplant.py
hgext/uncommit.py
hgext/win32mbcs.py
hgext/win32text.py
hgext/convert/__init__.py
hgext/convert/bzr.py
hgext/convert/common.py
hgext/convert/convcmd.py
hgext/convert/cvs.py
hgext/convert/cvsps.py
hgext/convert/darcs.py
hgext/convert/filemap.py
hgext/convert/git.py
hgext/convert/gnuarch.py
hgext/convert/hg.py
hgext/convert/monotone.py
hgext/convert/p4.py
hgext/convert/subversion.py
hgext/convert/transport.py
hgext/fastannotate/__init__.py
hgext/fastannotate/commands.py
hgext/fastannotate/context.py
hgext/fastannotate/error.py
hgext/fastannotate/formatter.py
hgext/fastannotate/protocol.py
hgext/fastannotate/revmap.py
hgext/fastannotate/support.py
hgext/fsmonitor/__init__.py
hgext/fsmonitor/state.py
hgext/fsmonitor/watchmanclient.py
hgext/fsmonitor/pywatchman/__init__.py
hgext/fsmonitor/pywatchman/bser.cpython-310-i386-linux-gnu.so
hgext/fsmonitor/pywatchman/capabilities.py
hgext/fsmonitor/pywatchman/compat.py
hgext/fsmonitor/pywatchman/encoding.py
hgext/fsmonitor/pywatchman/load.py
mercurial-7.2.dist-info/METADATA
mercurial-7.2.dist-info/WHEEL
mercurial-7.2.dist-info/top_level.txt
mercurial-7.2.dist-info/RECORD
mercurial-7.2.dist-info/licenses/COPYING
