Metadata-Version: 2.4
Name: mercurial
Version: 7.2
Summary: Fast scalable distributed SCM (revision control, version control) system
Author-email: Olivia Mackall and many others <mercurial@mercurial-scm.org>
License-Expression: GPL-2.0-or-later
Project-URL: home, https://mercurial-scm.org/
Project-URL: download_url, https://mercurial-scm.org/release/
Classifier: Development Status :: 6 - Mature
Classifier: Environment :: Console
Classifier: Intended Audience :: Developers
Classifier: Intended Audience :: System Administrators
Classifier: Natural Language :: Danish
Classifier: Natural Language :: English
Classifier: Natural Language :: German
Classifier: Natural Language :: Italian
Classifier: Natural Language :: Japanese
Classifier: Natural Language :: Portuguese (Brazilian)
Classifier: Operating System :: Microsoft :: Windows
Classifier: Operating System :: OS Independent
Classifier: Operating System :: POSIX
Classifier: Programming Language :: C
Classifier: Programming Language :: Python
Classifier: Topic :: Software Development :: Version Control
Requires-Python: >=3.9
License-File: COPYING
Provides-Extra: zstd
Requires-Dist: zstandard; extra == "zstd"
Dynamic: license-file
